mexa
