Metadata-Version: 2.1
Name: mexa
Version: 0.6
Summary: Validador y Generador de campos para tramites mexicanos
Home-page: https://github.com/fitorec/mexa-py
Author: @Fitorec - Miguel Angel Marcial Martinez
Author-email: fitorec@mundosica.com
License: MIT
Keywords: RFC,CURP,NSS,Clabe
Platform: UNKNOWN
Classifier: Programming Language :: Python :: 3.8
